openbb_stockgrid/__init__.py
openbb_stockgrid/models/short_volume.py
openbb_stockgrid-1.5.1.dist-info/METADATA
openbb_stockgrid-1.5.1.dist-info/WHEEL
openbb_stockgrid-1.5.1.dist-info/entry_points.txt
openbb_stockgrid-1.5.1.dist-info/RECORD
